{
  "body_path": "memory/architecture.md",
  "content_hash": "sha256:19614feb73a5e434d9a0ab4193fb1866aedefdddf83b3f71d5f7acc8e5fcfbdc",
  "created_at": "2026-05-01T18:44:07+02:00",
  "id": "architecture.current",
  "scope": {
    "branch": null,
    "kind": "project",
    "project": "project.aictx",
    "task": null
  },
  "source": {
    "kind": "cli",
    "task": "Proposed bootstrap memory patch from deterministic repository analysis"
  },
  "status": "active",
  "tags": [
    "architecture"
  ],
  "title": "Current Architecture",
  "type": "architecture",
  "updated_at": "2026-05-01T20:44:56+02:00"
}
